setup.py
pydslice/__init__.py
pydslice/pydslice.py
pydslice/pydslice_debugger.py
pydslice/pydslice_debugger_gdb.py
pydslice/pydslice_gdb_cmds.py
pydslice/pydslice_insn.py
pydslice/pydslice_operand.py
pydslice/pydslice_parser.py
pydslice/pydslice_parser_x86.py
pydslice/pydslice_parser_x86_64.py
pydslice/pydslice_plugin_abrt.py
pydslice/pydslice_x86_defs.py
pydslice.egg-info/PKG-INFO
pydslice.egg-info/SOURCES.txt
pydslice.egg-info/dependency_links.txt
pydslice.egg-info/top_level.txt