Metadata-Version: 1.1
Name: pydslice
Version: 1.0.2
Summary: Python library for computing dynamic slices using a debugger
Home-page: https://github.com/dev-burbrink/pydslice
Author: Josh Burbrink
Author-email: dev.burbrink@gmail.com
License: LGPL
Platform: any
Classifier: Development Status :: 4 - Beta
Classifier: Intended Audience :: Developers
Classifier: License :: OSI Approved :: GNU Lesser General Public License v3 (LGPLv3)
Classifier: Topic :: Software Development :: Libraries :: Application Frameworks
Classifier: Programming Language :: Python
